bidict/__init__.py
bidict/_abc.py
bidict/_base.py
bidict/_bidict.py
bidict/_delegating.py
bidict/_dup.py
bidict/_exc.py
bidict/_frozenbidict.py
bidict/_frozenordered.py
bidict/_iter.py
bidict/_mut.py
bidict/_named.py
bidict/_orderedbase.py
bidict/_orderedbidict.py
bidict/_typing.py
bidict/metadata.py
bidict/py.typed
bidict-0.21.3.dist-info/LICENSE
bidict-0.21.3.dist-info/METADATA
bidict-0.21.3.dist-info/WHEEL
bidict-0.21.3.dist-info/top_level.txt
bidict-0.21.3.dist-info/RECORD
