Metadata-Version: 2.1
Name: bidict
Version: 0.21.3
Summary: The bidirectional mapping library for Python.
Home-page: https://bidict.readthedocs.io
Author: Joshua Bronson
Author-email: jabronson@gmail.com
License: MPL 2.0
Keywords: dict dictionary mapping datastructure bimap bijection bijective injective inverse reverse bidirectional two-way 2-way
Platform: UNKNOWN
Classifier: Development Status :: 4 - Beta
Classifier: Intended Audience :: Developers
Classifier: License :: OSI Approved :: Mozilla Public License 2.0 (MPL 2.0)
Classifier: Operating System :: OS Independent
Classifier: Programming Language :: Python :: 3 :: Only
Classifier: Programming Language :: Python :: 3.6
Classifier: Programming Language :: Python :: 3.7
Classifier: Programming Language :: Python :: 3.8
Classifier: Programming Language :: Python :: 3.9
Classifier: Programming Language :: Python :: Implementation :: CPython
Classifier: Programming Language :: Python :: Implementation :: PyPy
Classifier: Topic :: Software Development :: Libraries :: Python Modules
Classifier: Typing :: Typed
Requires-Python: >=3.6
